exp1/__init__.py
src/YPPRPO.py
src/__init__.py
src/detectorDrop.py
src/widgets.py
almavik-281.dist-info/METADATA
almavik-281.dist-info/WHEEL
almavik-281.dist-info/top_level.txt
almavik-281.dist-info/RECORD
