Metadata-Version: 2.1
Name: almavik
Version: 281
Summary: Determination of the drop trajectory
Home-page: https://github.com/markusLons/almavik
Author: Markus.Alinas.Viktorias
Author-email: v.tikhonova@g.nsu.ru
Requires-Dist: opencv-python
Requires-Dist: numpy
Requires-Dist: PyQt5
Requires-Dist: matplotlib
